soapify/auth.py
soapify/cli.py
soapify/gatherer.py
soapify-1.0.2.dist-info/LICENSE
soapify-1.0.2.dist-info/METADATA
soapify-1.0.2.dist-info/WHEEL
soapify-1.0.2.dist-info/entry_points.txt
soapify-1.0.2.dist-info/top_level.txt
soapify-1.0.2.dist-info/RECORD
