Metadata-Version: 2.1
Name: soapify
Version: 1.0.2
Summary: search on your all spotify playlists
Home-page: https://github.com/tncga/soap
Author: tncga
Author-email: qokberk_akdeniz@hotmail.com
License: MIT
Keywords: spotify search playlist cli
Platform: UNKNOWN
Requires-Dist: click
Requires-Dist: spotipy
